MANIFEST.in
README.txt
setup.py
docs/HISTORY.txt
src/silva/__init__.py
src/silva.security.logging.egg-info/PKG-INFO
src/silva.security.logging.egg-info/SOURCES.txt
src/silva.security.logging.egg-info/dependency_links.txt
src/silva.security.logging.egg-info/namespace_packages.txt
src/silva.security.logging.egg-info/not-zip-safe
src/silva.security.logging.egg-info/requires.txt
src/silva.security.logging.egg-info/top_level.txt
src/silva/security/__init__.py
src/silva/security/logging/__init__.py
src/silva/security/logging/configure.zcml
src/silva/security/logging/entry.py
src/silva/security/logging/ftesting.zcml
src/silva/security/logging/interfaces.py
src/silva/security/logging/service.png
src/silva/security/logging/service.py
src/silva/security/logging/storage.py
src/silva/security/logging/subscribers.py
src/silva/security/logging/testing.py
src/silva/security/logging/service_templates/viewlog.pt
src/silva/security/logging/tests/__init__.py
src/silva/security/logging/tests/test_events.py
src/silva/security/logging/tests/test_service.py