Metadata-Version: 1.1
Name: silva.security.logging
Version: 1.2.2
Summary: Log all actions inside Silva CMS in a file or SQL table
Home-page: https://github.com/silvacms/silva.security.logging
Author: Infrae
Author-email: info@infrae.com
License: BSD
Keywords: silva cms zope security
Platform: UNKNOWN
Classifier: Framework :: Zope2
Classifier: License :: OSI Approved :: BSD License
Classifier: Programming Language :: Python
Classifier: Topic :: Software Development :: Libraries :: Python Modules
